{
    "code": "def check_auth(line_num: int, auth: str) -> List[str]:\n\n    err_msgs = []\n\n    backtick = '`'\n    if auth != 'No' and (not auth.startswith(backtick) or not auth.endswith(backtick)):\n        err_msg = error_message(line_num, 'auth value is not enclosed with `backticks`')\n        err_msgs.append(err_msg)\n\n    if auth.replace(backtick, '') not in auth_keys:\n        err_msg = error_message(line_num, f'{auth} is not a valid Auth option')\n        err_msgs.append(err_msg)\n    \n    return err_msgs",
    "source": "github_repo:public-apis/public-apis",
    "file": "scripts/validate/format.py",
    "license": "MIT",
    "language": "python"
}