{
    "code": "from .template import AlphaDataset\nfrom .utility import Segment, to_datetime\nfrom .processor import (\n    process_drop_na,\n    process_fill_na,\n    process_cs_norm,\n    process_robust_zscore_norm,\n    process_cs_rank_norm\n)\n\n\n__all__ = [\n    \"AlphaDataset\",\n    \"Segment\",\n    \"to_datetime\",\n    \"process_drop_na\",\n    \"process_fill_na\",\n    \"process_cs_norm\",\n    \"process_robust_zscore_norm\",\n    \"process_cs_rank_norm\"\n]",
    "source": "github_repo:vnpy/vnpy",
    "file": "vnpy/alpha/dataset/__init__.py",
    "license": "MIT",
    "language": "python"
}