{
    "code": "def construct(self):\n        title = Tex(r\"This is some \\LaTeX\")\n        basel = MathTex(r\"\\sum_{n=1}^\\infty \\frac{1}{n^2} = \\frac{\\pi^2}{6}\")\n        VGroup(title, basel).arrange(DOWN)\n        self.play(\n            Write(title),\n            FadeIn(basel, shift=DOWN),\n        )\n        self.wait()\n\n        transform_title = Tex(\"That was a transform\")\n        transform_title.to_corner(UP + LEFT)\n        self.play(\n            Transform(title, transform_title),\n            LaggedStart(*(FadeOut(obj, shift=DOWN) for obj in basel)),\n        )\n        self.wait()\n\n        grid = NumberPlane()\n        grid_title = Tex(\"This is a grid\", font_size=72)\n        grid_title.move_to(transform_title)\n\n        self.add(grid, grid_title)  # Make sure title is on top of grid\n        self.play(\n            FadeOut(title),\n            FadeIn(grid_title, shift=UP),\n            Create(grid, run_time=3, lag_ratio=0.1),\n        )\n        self.wait()\n\n        grid_transform_title = Tex(\n            r\"That was a non-linear function \\\\ applied to the grid\",\n        )\n        grid_transform_title.move_to(grid_title, UL)\n        grid.prepare_for_nonlinear_transform()\n        self.play(\n            grid.animate.apply_function(\n                lambda p: p\n                + np.array(\n                    [\n                        np.sin(p[1]),\n                        np.sin(p[0]),\n                        0,\n                    ],\n                ),\n            ),\n            run_time=3,\n        )\n        self.wait()\n        self.play(Transform(grid_title, grid_transform_title))\n        self.wait()",
    "source": "github_repo:ManimCommunity/manim",
    "file": "example_scenes/basic.py",
    "license": "MIT",
    "language": "python"
}